primehub/VERSION
primehub/__init__.py
primehub/admin_groups.py
primehub/admin_images.py
primehub/admin_instancetypes.py
primehub/admin_reports.py
primehub/admin_secrets.py
primehub/admin_users.py
primehub/admin_volumes.py
primehub/apps.py
primehub/apptemplates.py
primehub/cli.py
primehub/config.py
primehub/datasets.py
primehub/deployments.py
primehub/files.py
primehub/groups.py
primehub/images.py
primehub/info.py
primehub/instancetypes.py
primehub/jobs.py
primehub/me.py
primehub/models.py
primehub/notebooks.py
primehub/recurring_jobs.py
primehub/resource_operations.py
primehub/secrets.py
primehub/version.py
primehub/volumes.py
primehub/extras/__init__.py
primehub/extras/devlab.py
primehub/extras/doc_generator.py
primehub/extras/e2e.py
primehub/utils/__init__.py
primehub/utils/completion.py
primehub/utils/core.py
primehub/utils/decorators.py
primehub/utils/display.py
primehub/utils/http_client.py
primehub/utils/optionals.py
primehub/utils/permission.py
primehub/utils/validator.py
primehub/utils/argparser/__init__.py
tests/__init__.py
tests/graphql_formatter.py
tests/test_admin_groups.py
tests/test_admin_images.py
tests/test_admin_instancetypes.py
tests/test_admin_users.py
tests/test_cli_config.py
tests/test_cmd_config.py
tests/test_cmd_me.py
tests/test_config.py
tests/test_datasets.py
tests/test_files.py
tests/test_graphql_lint.py
tests/test_group_resource_operation.py
tests/test_http_utils.py
tests/test_implementation_in_source_level.py
tests/test_jobs.py
tests/test_output_utils.py
tests/test_print.py
tests/test_recurring_jobs.py
tests/test_sdk_to_admin_cli.py
tests/test_sdk_to_cli.py
tests/test_sdk_to_cli_module_alias.py
tests/test_test_utils.py
tests/test_validator_tools.py
tests/test_volumes.py
primehub_python_sdk-0.4.2.dist-info/LICENSE
primehub_python_sdk-0.4.2.dist-info/METADATA
primehub_python_sdk-0.4.2.dist-info/WHEEL
primehub_python_sdk-0.4.2.dist-info/entry_points.txt
primehub_python_sdk-0.4.2.dist-info/top_level.txt
primehub_python_sdk-0.4.2.dist-info/RECORD
