Metadata-Version: 2.1
Name: primehub-python-sdk
Version: 0.4.2
Summary: PrimeHub Python SDK
Home-page: https://github.com/InfuseAI/primehub-python-sdk
Author: qrtt1
Author-email: qrtt1@infuseai.io
Project-URL: Bug Tracker, https://github.com/InfuseAI/primehub/issues
Classifier: Programming Language :: Python :: 3
Classifier: License :: OSI Approved :: Apache Software License
Classifier: Operating System :: OS Independent
Classifier: Development Status :: 4 - Beta
Requires-Python: >=3.6
License-File: LICENSE
Requires-Dist: requests
Requires-Dist: tabulate (==0.8.9)
Requires-Dist: types-tabulate (==0.8.2)
Requires-Dist: types-requests
Provides-Extra: dev
Requires-Dist: pytest (>=4.6) ; extra == 'dev'
Requires-Dist: pytest-flake8 ; extra == 'dev'
Requires-Dist: flake8 (==3.9.2) ; extra == 'dev'
Requires-Dist: pytest-mypy ; extra == 'dev'
Requires-Dist: pytest-cov ; extra == 'dev'
Requires-Dist: Jinja2 ; extra == 'dev'
Requires-Dist: types-Jinja2 ; extra == 'dev'
Requires-Dist: twine ; extra == 'dev'
Requires-Dist: importlib-metadata (<5) ; extra == 'dev'
